pylspclient/__init__.py
pylspclient/json_rpc_endpoint.py
pylspclient/lsp_client.py
pylspclient/lsp_endpoint.py
pylspclient/lsp_errors.py
pylspclient/lsp_pydantic_strcuts.py
pylspclient-0.1.2.dist-info/LICENSE
pylspclient-0.1.2.dist-info/METADATA
pylspclient-0.1.2.dist-info/WHEEL
pylspclient-0.1.2.dist-info/RECORD
