Metadata-Version: 2.1
Name: pylspclient
Version: 0.1.2
Summary: LSP client implementation in Python
Author: yeger00
Author-email: yeger00@gmail.com
Requires-Python: >=3.10,<4.0
Classifier: Programming Language :: Python :: 3
Classifier: Programming Language :: Python :: 3.10
Classifier: Programming Language :: Python :: 3.11
Classifier: Programming Language :: Python :: 3.12
Requires-Dist: mypy (>=1.9.0,<2.0.0)
Requires-Dist: pydantic (>=2.5.2,<3.0.0)
